{
  "segmentId": "SEGMENT_02_01_02_MBEANS_EXPLAINED_V2",
  "segmentType": "concept_explanation",
  "title": "MBeans: Your Window into Java Applications",
  "text": "At its core, JMX revolves around MBeans\u2014Managed Beans. An MBean is just a Java object that exposes attributes (metrics) and operations (actions). Each MBean has a unique ObjectName following a pattern like: kafka.server:type=BrokerTopicMetrics,name=BytesInPerSec",
  "audioId": "AUDIO_SEG02_01_02_MBEANS_V2",
  "generatedAt": "2025-06-01T02:33:09.629744",
  "audioFile": "AUDIO_SEG02_01_02_MBEANS_V2.mp3",
  "voice": "en-US-ChristopherNeural",
  "audioGenerated": true,
  "voiceType": "adult_professional"
}